runtype/__init__.py
runtype/base_types.py
runtype/cast.py
runtype/casts/debug_repr.py
runtype/casts/measurements.py
runtype/common.py
runtype/dataclass.py
runtype/datetime_parse.py
runtype/dispatch.py
runtype/py.typed
runtype/pytypes.py
runtype/typesystem.py
runtype/utils.py
runtype/validation.py
runtype-0.5.2.dist-info/LICENSE
runtype-0.5.2.dist-info/METADATA
runtype-0.5.2.dist-info/WHEEL
runtype-0.5.2.dist-info/RECORD
