Metadata-Version: 2.1
Name: runtype
Version: 0.5.2
Summary: Type dispatch and validation for run-time Python
Home-page: https://github.com/erezsh/runtype
License: MIT
Keywords: types,typing,dispatch,multimethods,dataclass,runtime
Author: Erez Shinan
Author-email: erezshin@gmail.com
Requires-Python: >=3.8,<4.0
Classifier: Development Status :: 5 - Production/Stable
Classifier: Intended Audience :: Developers
Classifier: License :: OSI Approved :: MIT License
Classifier: Programming Language :: Python :: 3
Classifier: Programming Language :: Python :: 3.8
Classifier: Programming Language :: Python :: 3.9
Classifier: Programming Language :: Python :: 3.10
Classifier: Programming Language :: Python :: 3.11
Classifier: Programming Language :: Python :: 3.12
Classifier: Topic :: Software Development :: Libraries :: Python Modules
Classifier: Topic :: Software Development :: Quality Assurance
Classifier: Topic :: Utilities
Project-URL: Repository, https://github.com/erezsh/runtype
